sphinx_stylo/__init__.py
sphinx_stylo/_version.py
sphinx_stylo/directives.py
sphinx_stylo/templates.py
sphinx_stylo-0.1.1.dist-info/LICENSE
sphinx_stylo-0.1.1.dist-info/METADATA
sphinx_stylo-0.1.1.dist-info/WHEEL
sphinx_stylo-0.1.1.dist-info/top_level.txt
sphinx_stylo-0.1.1.dist-info/RECORD
