Metadata-Version: 2.1
Name: sphinx-stylo
Version: 0.1.1
Summary: Insert images into Sphinx documentation using inline code and stylo
Home-page: https://github.com/alcarney/sphinx-stylo
Author: Alex Carney
Author-email: alcarneyme@gmail.com
License: MIT
Platform: UNKNOWN
Classifier: Development Status :: 3 - Alpha
Classifier: License :: OSI Approved :: MIT License
Classifier: Programming Language :: Python :: 3.7
Classifier: Programming Language :: Python :: 3 :: Only
Classifier: Topic :: Documentation
Classifier: Topic :: Documentation :: Sphinx
Requires-Python: >=3.5
Requires-Dist: sphinx
Requires-Dist: stylo
